pycotools3/__init__.py
pycotools3/_base.py
pycotools3/bunch.py
pycotools3/cached_property.py
pycotools3/errors.py
pycotools3/misc.py
pycotools3/mixin.py
pycotools3/model.py
pycotools3/tasks.py
pycotools3/utils.py
pycotools3/viz.py
pycotools3-2.1.22.dist-info/METADATA
pycotools3-2.1.22.dist-info/WHEEL
pycotools3-2.1.22.dist-info/top_level.txt
pycotools3-2.1.22.dist-info/RECORD
