Metadata-Version: 2.1
Name: pycotools3
Version: 2.1.22
Summary: A python toolbox for COPASI
Home-page: https://github.com/CiaranWelsh/pycotools3
Author: Ciaran Welsh
Author-email: ciaran.welsh@newcastle.ac.uk
License: GPL4
Keywords: systems biology,modelling,biological,networks,copasi,identifiability analysis,profile likelihood
Platform: UNKNOWN
Requires: lxml
Requires: argparse
Requires: pandas
Requires: numpy
Requires: scipy
Requires: matplotlib
Requires: scipy
Requires: seaborn
Requires: sklearn
Requires: retrying
Requires: psutil
Requires: tellurium
Requires: pyyaml
Requires: json
Requires: deprecated
Requires: pyyaml
Requires: pyqt5
Requires-Python: >=3
Requires-Dist: pandas
Requires-Dist: numpy
Requires-Dist: scipy
Requires-Dist: matplotlib
Requires-Dist: lxml
Requires-Dist: seaborn
Requires-Dist: sklearn
Requires-Dist: psutil
Requires-Dist: tellurium
Requires-Dist: pyyaml
Requires-Dist: munch
Requires-Dist: pathos
Requires-Dist: nose
Requires-Dist: nbsphinx
Requires-Dist: PyYAML
Requires-Dist: sphinx-rtd-theme
Provides-Extra: docs
Requires-Dist: sphinx (>=1.4) ; extra == 'docs'
Requires-Dist: sphinx-rtd-theme ; extra == 'docs'
